music_playlists/__about__.py
music_playlists/__init__.py
music_playlists/__main__.py
music_playlists/intermediate.py
music_playlists/model.py
music_playlists/process.py
music_playlists/settings.py
music_playlists/utils.py
music_playlists/cli/__init__.py
music_playlists/services/__init__.py
music_playlists/services/spotify.py
music_playlists/services/youtube_music.py
music_playlists/sources/__init__.py
music_playlists/sources/abc_radio.py
music_playlists/sources/last_fm.py
music_playlists/sources/radio_4zzz.py
music_playlists-0.3.1.dist-info/METADATA
music_playlists-0.3.1.dist-info/WHEEL
music_playlists-0.3.1.dist-info/entry_points.txt
music_playlists-0.3.1.dist-info/licenses/LICENSE.txt
music_playlists-0.3.1.dist-info/RECORD
