Metadata-Version: 2.4
Name: music-playlists
Version: 0.3.1
Summary: Generates streaming music playlists from various song charts.
Project-URL: Documentation, https://github.com/cofiem/music-playlists#readme
Project-URL: Issues, https://github.com/cofiem/music-playlists/issues
Project-URL: Source, https://github.com/cofiem/music-playlists
Project-URL: Changelog, https://github.com/cofiem/music-playlists/blob/main/CHANGELOG.md
Author-email: Mark C <cofiem@gmail.com>
License-Expression: Apache-2.0
License-File: LICENSE.txt
Keywords: music,playlist
Classifier: Development Status :: 4 - Beta
Classifier: Environment :: Console
Classifier: License :: OSI Approved :: Apache Software License
Classifier: Programming Language :: Python
Classifier: Programming Language :: Python :: 3
Classifier: Programming Language :: Python :: 3 :: Only
Classifier: Programming Language :: Python :: 3.12
Classifier: Programming Language :: Python :: 3.13
Classifier: Programming Language :: Python :: 3.14
Classifier: Programming Language :: Python :: Implementation :: CPython
Classifier: Programming Language :: Python :: Implementation :: PyPy
Classifier: Topic :: Multimedia :: Sound/Audio
Requires-Python: >=3.12
Requires-Dist: attrs==25.4.0
Requires-Dist: beartype==0.22.9
Requires-Dist: cattrs==25.3.0
Requires-Dist: click==8.3.1
Requires-Dist: lxml==6.0.2
Requires-Dist: requests-cache==1.2.1
Requires-Dist: requests==2.32.5
Requires-Dist: rich==14.2.0
Requires-Dist: tzdata==2025.3
Requires-Dist: ytmusicapi==1.11.4
